lib/__init__.py
cyberscript-0.0.1.dist-info/LICENSE
cyberscript-0.0.1.dist-info/METADATA
cyberscript-0.0.1.dist-info/WHEEL
cyberscript-0.0.1.dist-info/RECORD
