Metadata-Version: 2.1
Name: cyberscript
Version: 0.0.1
Summary: An AI web browsing framework focused on simplicity and extensibility.
License: MIT
Author: Div Garg
Author-email: divyansh199@gmail.com
Requires-Python: >=3.8,<4.0
Classifier: License :: OSI Approved :: MIT License
Classifier: Programming Language :: Python :: 3
Classifier: Programming Language :: Python :: 3.8
Classifier: Programming Language :: Python :: 3.9
Classifier: Programming Language :: Python :: 3.10
Classifier: Programming Language :: Python :: 3.11
